interfacedoc/__init__.py
interfacedoc/installer.py
interfacedoc/run.py
interfacedoc-0.0.3.dist-info/LICENCE.txt
interfacedoc-0.0.3.dist-info/METADATA
interfacedoc-0.0.3.dist-info/WHEEL
interfacedoc-0.0.3.dist-info/entry_points.txt
interfacedoc-0.0.3.dist-info/top_level.txt
interfacedoc-0.0.3.dist-info/RECORD
